tse/__init__.py
tse/epson.py
tse/exceptions.py
tse.py-1.0.4.dist-info/LICENSE
tse.py-1.0.4.dist-info/METADATA
tse.py-1.0.4.dist-info/WHEEL
tse.py-1.0.4.dist-info/top_level.txt
tse.py-1.0.4.dist-info/RECORD
