Metadata-Version: 2.1
Name: tse.py
Version: 1.0.4
Summary: A Python package to access security modules (TSE) of the German Fiscal Authority.
Home-page: https://gitlab.com/ccodein/tse.py
Author: lluar
Author-email: lluar@ccodein.org
License: MIT
Platform: any
Requires-Python: >=3.10
License-File: LICENSE
Provides-Extra: develop
Requires-Dist: pytest ; extra == 'develop'
Requires-Dist: pytest-cov ; extra == 'develop'
Requires-Dist: mypy ; extra == 'develop'
Requires-Dist: flake8 ; extra == 'develop'
Requires-Dist: flake8-docstrings ; extra == 'develop'
Requires-Dist: sphinx ; extra == 'develop'
Requires-Dist: sphinx-rtd-theme ; extra == 'develop'
Requires-Dist: sphinxcontrib-mermaid ; extra == 'develop'
